odoo/addons/test_mail_private/README.rst
odoo/addons/test_mail_private/__init__.py
odoo/addons/test_mail_private/__manifest__.py
odoo/addons/test_mail_private/i18n/test_mail_private.pot
odoo/addons/test_mail_private/readme/CONTRIBUTORS.rst
odoo/addons/test_mail_private/readme/DESCRIPTION.rst
odoo/addons/test_mail_private/static/description/icon.png
odoo/addons/test_mail_private/static/description/index.html
odoo/addons/test_mail_private/tests/__init__.py
odoo/addons/test_mail_private/tests/test_mail_private.py
odoo12_addon_test_mail_private-12.0.1.0.2.dist-info/METADATA
odoo12_addon_test_mail_private-12.0.1.0.2.dist-info/WHEEL
odoo12_addon_test_mail_private-12.0.1.0.2.dist-info/top_level.txt
odoo12_addon_test_mail_private-12.0.1.0.2.dist-info/RECORD
